kcwsqlite
