Metadata-Version: 1.2
Name: kcwsqlite
Version: 3.32
Summary: kcwsqlite
Home-page: UNKNOWN
Author: 百里
Author-email: kcwebs@kwebapp.cn
Maintainer: 坤坤
Maintainer-email: fk1402936534@qq.com
License: MIT License
Keywords: kcwsqlite3.32
Platform: UNKNOWN
